{"apps":{"http":{"servers":{"srv0":{"listen":[":443"],"routes":[{"handle":[{"handler":"subroute","routes":[{"handle":[{"handler":"vars","root":"/2311test/public"},{"encodings":{"gzip":{}},"handler":"encode","prefer":["gzip"]}]},{"handle":[{"handler":"static_response","headers":{"Location":["{http.request.orig_uri.path}/"]},"status_code":308}],"match":[{"file":{"try_files":["{http.request.uri.path}/index.php"]},"not":[{"path":["*/"]}]}]},{"handle":[{"handler":"rewrite","uri":"{http.matchers.file.relative}"}],"match":[{"file":{"split_path":[".php"],"try_files":["{http.request.uri.path}","{http.request.uri.path}/index.php","index.php"]}}]},{"handle":[{"handler":"reverse_proxy","transport":{"protocol":"fastcgi","split_path":[".php"]},"upstreams":[{"dial":"2311test:9000"}]}],"match":[{"path":["*.php"]}]},{"handle":[{"handler":"file_server","hide":["./Caddyfile"]}]}]}],"match":[{"host":["localhost"]}],"terminal":true},{"handle":[{"handler":"subroute","routes":[{"handle":[{"body":"ещё чуть чуть и вот вот, а пока идите сюда \u003e \u003ca href='https://php-cat.com' target='_blank' \u003ephp-cat.com\u003c/a\u003e","handler":"static_response"}]}]}],"match":[{"host":["*.ru","*.xn--p1ai","*.com","*.info"]}],"terminal":true}]}}},"tls":{"automation":{"policies":[{"issuers":[{"module":"internal"}],"subjects":["*.com","*.info","*.ru","*.xn--p1ai","localhost"]}]}}}}